<?xml version='1.0' encoding='UTF-8'?>
<cfdi:Comprobante xmlns:cfdi="http://www.sat.gob.mx/cfd/4" xmlns:tfd="http://www.sat.gob.mx/TimbreFiscalDigital" xmlns:xsi="http://www.w3.org/2001/XMLSchema-instance" Version="4.0" Serie="A" Folio="A-619066" Fecha="2022-10-30T15:37:00" SubTotal="41301.47" Total="47909.71" TipoDeComprobante="I" MetodoPago="PUE" FormaPago="28" Moneda="MXN">
  <cfdi:Emisor Rfc="ANO850312AB1" Nombre="ACEROS DEL NORTE SA DE CV" RegimenFiscal="601"/>
  <cfdi:Receptor Rfc="SER950318BC1" Nombre="SERVICIOS ESPECIALIZADOS SA DE CV" UsoCFDI="I01" RegimenFiscalReceptor="601" DomicilioFiscalReceptor="64000"/>
  <cfdi:Conceptos>
    <cfdi:Concepto ClaveProdServ="76111500" Cantidad="47" ClaveUnidad="H87" Descripcion="Servicio de mantenimiento industrial" ValorUnitario="5900.21" Importe="41301.47"/>
  </cfdi:Conceptos>
  <cfdi:Impuestos TotalImpuestosTrasladados="6608.24">
    <cfdi:Traslados>
      <cfdi:Traslado Base="41301.47" Impuesto="002" TipoFactor="Tasa" TasaOCuota="0.160000" Importe="6608.24"/>
    </cfdi:Traslados>
  </cfdi:Impuestos>
  <cfdi:Complemento>
    <tfd:TimbreFiscalDigital Version="1.1" UUID="A1752E56-F501-4AE1-B965-4842F6E9584D" FechaTimbrado="2022-10-30T15:37:00" NoCertificadoSAT="20001000000300022323" SelloCFD="SIMULADO" SelloSAT="SIMULADO"/>
  </cfdi:Complemento>
</cfdi:Comprobante>
