<?xml version='1.0' encoding='UTF-8'?>
<cfdi:Comprobante xmlns:cfdi="http://www.sat.gob.mx/cfd/4" xmlns:tfd="http://www.sat.gob.mx/TimbreFiscalDigital" xmlns:xsi="http://www.w3.org/2001/XMLSchema-instance" Version="4.0" Serie="A" Folio="A-190940" Fecha="2022-12-13T13:42:00" SubTotal="37696.38" Total="43727.8" TipoDeComprobante="I" MetodoPago="PPD" FormaPago="03" Moneda="MXN">
  <cfdi:Emisor Rfc="ANO850312AB1" Nombre="ACEROS DEL NORTE SA DE CV" RegimenFiscal="601"/>
  <cfdi:Receptor Rfc="TMA011228PQ3" Nombre="TRANSPORTES MARTINEZ SA DE CV" UsoCFDI="I01" RegimenFiscalReceptor="601" DomicilioFiscalReceptor="64000"/>
  <cfdi:Conceptos>
    <cfdi:Concepto ClaveProdServ="72103200" Cantidad="54" ClaveUnidad="H87" Descripcion="Servicio de soldadura MIG/TIG" ValorUnitario="3769.64" Importe="37696.38"/>
  </cfdi:Conceptos>
  <cfdi:Impuestos TotalImpuestosTrasladados="6031.42">
    <cfdi:Traslados>
      <cfdi:Traslado Base="37696.38" Impuesto="002" TipoFactor="Tasa" TasaOCuota="0.160000" Importe="6031.42"/>
    </cfdi:Traslados>
  </cfdi:Impuestos>
  <cfdi:Complemento>
    <tfd:TimbreFiscalDigital Version="1.1" UUID="0DDA4C6B-F5CE-4090-BEFC-9E2E2DA7D46B" FechaTimbrado="2022-12-13T13:42:00" NoCertificadoSAT="20001000000300022323" SelloCFD="SIMULADO" SelloSAT="SIMULADO"/>
  </cfdi:Complemento>
</cfdi:Comprobante>
