<?xml version='1.0' encoding='UTF-8'?>
<cfdi:Comprobante xmlns:cfdi="http://www.sat.gob.mx/cfd/4" xmlns:tfd="http://www.sat.gob.mx/TimbreFiscalDigital" xmlns:xsi="http://www.w3.org/2001/XMLSchema-instance" Version="4.0" Serie="A" Folio="A-388331" Fecha="2023-09-16T13:23:00" SubTotal="23951.94" Total="27784.25" TipoDeComprobante="I" MetodoPago="PUE" FormaPago="04" Moneda="MXN">
  <cfdi:Emisor Rfc="ANO850312AB1" Nombre="ACEROS DEL NORTE SA DE CV" RegimenFiscal="601"/>
  <cfdi:Receptor Rfc="TEC040817FG3" Nombre="TECNOLOGIA INDUSTRIAL SA DE CV" UsoCFDI="I01" RegimenFiscalReceptor="601" DomicilioFiscalReceptor="64000"/>
  <cfdi:Conceptos>
    <cfdi:Concepto ClaveProdServ="31201500" Cantidad="67" ClaveUnidad="H87" Descripcion="Pintura epóxica industrial" ValorUnitario="7983.98" Importe="23951.94"/>
  </cfdi:Conceptos>
  <cfdi:Impuestos TotalImpuestosTrasladados="3832.31">
    <cfdi:Traslados>
      <cfdi:Traslado Base="23951.94" Impuesto="002" TipoFactor="Tasa" TasaOCuota="0.160000" Importe="3832.31"/>
    </cfdi:Traslados>
  </cfdi:Impuestos>
  <cfdi:Complemento>
    <tfd:TimbreFiscalDigital Version="1.1" UUID="79363DFE-03D7-4F14-8F06-C7298F8DB141" FechaTimbrado="2023-09-16T13:23:00" NoCertificadoSAT="20001000000300022323" SelloCFD="SIMULADO" SelloSAT="SIMULADO"/>
  </cfdi:Complemento>
</cfdi:Comprobante>
