<?xml version='1.0' encoding='UTF-8'?>
<cfdi:Comprobante xmlns:cfdi="http://www.sat.gob.mx/cfd/4" xmlns:tfd="http://www.sat.gob.mx/TimbreFiscalDigital" xmlns:xsi="http://www.w3.org/2001/XMLSchema-instance" Version="4.0" Serie="A" Folio="A-776244" Fecha="2022-01-16T17:18:00" SubTotal="472092.84849715413" Total="547627.71" TipoDeComprobante="I" MetodoPago="PPD" FormaPago="28" Moneda="MXN">
  <cfdi:Emisor Rfc="ANO850312AB1" Nombre="ACEROS DEL NORTE SA DE CV" RegimenFiscal="601"/>
  <cfdi:Receptor Rfc="PRO760415VW9" Nombre="PROVEEDORA REGIOMONTANA SA DE CV" UsoCFDI="G01" RegimenFiscalReceptor="601" DomicilioFiscalReceptor="64000"/>
  <cfdi:Conceptos>
    <cfdi:Concepto ClaveProdServ="72154400" Cantidad="80" ClaveUnidad="H87" Descripcion="Lámina de acero galvanizado calibre 20" ValorUnitario="67441.84" Importe="472092.84849715413"/>
  </cfdi:Conceptos>
  <cfdi:Impuestos TotalImpuestosTrasladados="75534.86">
    <cfdi:Traslados>
      <cfdi:Traslado Base="472092.84849715413" Impuesto="002" TipoFactor="Tasa" TasaOCuota="0.160000" Importe="75534.86"/>
    </cfdi:Traslados>
  </cfdi:Impuestos>
  <cfdi:Complemento>
    <tfd:TimbreFiscalDigital Version="1.1" UUID="D99FD8B8-E636-422F-9187-7D1F09F4BC05" FechaTimbrado="2022-01-16T17:18:00" NoCertificadoSAT="20001000000300022323" SelloCFD="SIMULADO" SelloSAT="SIMULADO"/>
  </cfdi:Complemento>
</cfdi:Comprobante>
