<?xml version='1.0' encoding='UTF-8'?>
<cfdi:Comprobante xmlns:cfdi="http://www.sat.gob.mx/cfd/4" xmlns:tfd="http://www.sat.gob.mx/TimbreFiscalDigital" xmlns:xsi="http://www.w3.org/2001/XMLSchema-instance" Version="4.0" Serie="A" Folio="A-232889" Fecha="2024-03-16T08:24:00" SubTotal="4742.96" Total="5501.83" TipoDeComprobante="I" MetodoPago="PUE" FormaPago="04" Moneda="MXN">
  <cfdi:Emisor Rfc="ANO850312AB1" Nombre="ACEROS DEL NORTE SA DE CV" RegimenFiscal="601"/>
  <cfdi:Receptor Rfc="FIN920315KL8" Nombre="FERRETERIA INDUSTRIAL DEL NORTE SA DE CV" UsoCFDI="G03" RegimenFiscalReceptor="601" DomicilioFiscalReceptor="64000"/>
  <cfdi:Conceptos>
    <cfdi:Concepto ClaveProdServ="31201500" Cantidad="69" ClaveUnidad="H87" Descripcion="Pintura epóxica industrial" ValorUnitario="948.59" Importe="4742.96"/>
  </cfdi:Conceptos>
  <cfdi:Impuestos TotalImpuestosTrasladados="758.87">
    <cfdi:Traslados>
      <cfdi:Traslado Base="4742.96" Impuesto="002" TipoFactor="Tasa" TasaOCuota="0.160000" Importe="758.87"/>
    </cfdi:Traslados>
  </cfdi:Impuestos>
  <cfdi:Complemento>
    <tfd:TimbreFiscalDigital Version="1.1" UUID="664E3E8F-4A0D-4F8D-A84A-735828192DAA" FechaTimbrado="2024-03-16T08:24:00" NoCertificadoSAT="20001000000300022323" SelloCFD="SIMULADO" SelloSAT="SIMULADO"/>
  </cfdi:Complemento>
</cfdi:Comprobante>
