<?xml version='1.0' encoding='UTF-8'?>
<cfdi:Comprobante xmlns:cfdi="http://www.sat.gob.mx/cfd/4" xmlns:tfd="http://www.sat.gob.mx/TimbreFiscalDigital" xmlns:xsi="http://www.w3.org/2001/XMLSchema-instance" Version="4.0" Serie="A" Folio="A-579089" Fecha="2022-04-08T13:04:00" SubTotal="43398.47" Total="50342.23" TipoDeComprobante="I" MetodoPago="PUE" FormaPago="28" Moneda="MXN">
  <cfdi:Emisor Rfc="ANO850312AB1" Nombre="ACEROS DEL NORTE SA DE CV" RegimenFiscal="601"/>
  <cfdi:Receptor Rfc="TMA011228PQ3" Nombre="TRANSPORTES MARTINEZ SA DE CV" UsoCFDI="G03" RegimenFiscalReceptor="601" DomicilioFiscalReceptor="64000"/>
  <cfdi:Conceptos>
    <cfdi:Concepto ClaveProdServ="80101500" Cantidad="90" ClaveUnidad="H87" Descripcion="Consultoría en procesos industriales" ValorUnitario="21699.24" Importe="43398.47"/>
  </cfdi:Conceptos>
  <cfdi:Impuestos TotalImpuestosTrasladados="6943.76">
    <cfdi:Traslados>
      <cfdi:Traslado Base="43398.47" Impuesto="002" TipoFactor="Tasa" TasaOCuota="0.160000" Importe="6943.76"/>
    </cfdi:Traslados>
  </cfdi:Impuestos>
  <cfdi:Complemento>
    <tfd:TimbreFiscalDigital Version="1.1" UUID="6E687844-A862-4CC9-B2C2-E1EE4607F3DB" FechaTimbrado="2022-04-08T13:04:00" NoCertificadoSAT="20001000000300022323" SelloCFD="SIMULADO" SelloSAT="SIMULADO"/>
  </cfdi:Complemento>
</cfdi:Comprobante>
