<?xml version='1.0' encoding='UTF-8'?>
<cfdi:Comprobante xmlns:cfdi="http://www.sat.gob.mx/cfd/4" xmlns:tfd="http://www.sat.gob.mx/TimbreFiscalDigital" xmlns:xsi="http://www.w3.org/2001/XMLSchema-instance" Version="4.0" Serie="A" Folio="A-564783" Fecha="2024-12-13T08:14:00" SubTotal="3640.51" Total="4222.99" TipoDeComprobante="I" MetodoPago="PPD" FormaPago="01" Moneda="MXN">
  <cfdi:Emisor Rfc="ANO850312AB1" Nombre="ACEROS DEL NORTE SA DE CV" RegimenFiscal="601"/>
  <cfdi:Receptor Rfc="MAT010925DE5" Nombre="MATERIALES Y CONSTRUCCION SA DE CV" UsoCFDI="I03" RegimenFiscalReceptor="601" DomicilioFiscalReceptor="64000"/>
  <cfdi:Conceptos>
    <cfdi:Concepto ClaveProdServ="31161500" Cantidad="54" ClaveUnidad="H87" Descripcion="Tornillería industrial especializada" ValorUnitario="3640.51" Importe="3640.51"/>
  </cfdi:Conceptos>
  <cfdi:Impuestos TotalImpuestosTrasladados="582.48">
    <cfdi:Traslados>
      <cfdi:Traslado Base="3640.51" Impuesto="002" TipoFactor="Tasa" TasaOCuota="0.160000" Importe="582.48"/>
    </cfdi:Traslados>
  </cfdi:Impuestos>
  <cfdi:Complemento>
    <tfd:TimbreFiscalDigital Version="1.1" UUID="843E6B2B-01A7-4A1B-96A5-CCEF3DC6A365" FechaTimbrado="2024-12-13T08:14:00" NoCertificadoSAT="20001000000300022323" SelloCFD="SIMULADO" SelloSAT="SIMULADO"/>
  </cfdi:Complemento>
</cfdi:Comprobante>
