<?xml version='1.0' encoding='UTF-8'?>
<cfdi:Comprobante xmlns:cfdi="http://www.sat.gob.mx/cfd/4" xmlns:tfd="http://www.sat.gob.mx/TimbreFiscalDigital" xmlns:xsi="http://www.w3.org/2001/XMLSchema-instance" Version="4.0" Serie="A" Folio="A-965352" Fecha="2025-01-12T08:22:00" SubTotal="8520.27" Total="9883.51" TipoDeComprobante="I" MetodoPago="PPD" FormaPago="28" Moneda="MXN">
  <cfdi:Emisor Rfc="ANO850312AB1" Nombre="ACEROS DEL NORTE SA DE CV" RegimenFiscal="601"/>
  <cfdi:Receptor Rfc="PRO760415VW9" Nombre="PROVEEDORA REGIOMONTANA SA DE CV" UsoCFDI="I01" RegimenFiscalReceptor="601" DomicilioFiscalReceptor="64000"/>
  <cfdi:Conceptos>
    <cfdi:Concepto ClaveProdServ="76111500" Cantidad="39" ClaveUnidad="H87" Descripcion="Servicio de mantenimiento industrial" ValorUnitario="1704.05" Importe="8520.27"/>
  </cfdi:Conceptos>
  <cfdi:Impuestos TotalImpuestosTrasladados="1363.24">
    <cfdi:Traslados>
      <cfdi:Traslado Base="8520.27" Impuesto="002" TipoFactor="Tasa" TasaOCuota="0.160000" Importe="1363.24"/>
    </cfdi:Traslados>
  </cfdi:Impuestos>
  <cfdi:Complemento>
    <tfd:TimbreFiscalDigital Version="1.1" UUID="ED457C8C-0A75-4108-A304-0447A273A27F" FechaTimbrado="2025-01-12T08:22:00" NoCertificadoSAT="20001000000300022323" SelloCFD="SIMULADO" SelloSAT="SIMULADO"/>
  </cfdi:Complemento>
</cfdi:Comprobante>
