<?xml version='1.0' encoding='UTF-8'?>
<cfdi:Comprobante xmlns:cfdi="http://www.sat.gob.mx/cfd/4" xmlns:tfd="http://www.sat.gob.mx/TimbreFiscalDigital" xmlns:xsi="http://www.w3.org/2001/XMLSchema-instance" Version="4.0" Serie="A" Folio="A-174225" Fecha="2023-10-22T14:24:00" SubTotal="33295.76" Total="38623.08" TipoDeComprobante="I" MetodoPago="PUE" FormaPago="01" Moneda="MXN">
  <cfdi:Emisor Rfc="ANO850312AB1" Nombre="ACEROS DEL NORTE SA DE CV" RegimenFiscal="601"/>
  <cfdi:Receptor Rfc="SER950318BC1" Nombre="SERVICIOS ESPECIALIZADOS SA DE CV" UsoCFDI="G03" RegimenFiscalReceptor="601" DomicilioFiscalReceptor="64000"/>
  <cfdi:Conceptos>
    <cfdi:Concepto ClaveProdServ="11101700" Cantidad="60" ClaveUnidad="H87" Descripcion="Materia prima aluminio extruido" ValorUnitario="6659.15" Importe="33295.76"/>
  </cfdi:Conceptos>
  <cfdi:Impuestos TotalImpuestosTrasladados="5327.32">
    <cfdi:Traslados>
      <cfdi:Traslado Base="33295.76" Impuesto="002" TipoFactor="Tasa" TasaOCuota="0.160000" Importe="5327.32"/>
    </cfdi:Traslados>
  </cfdi:Impuestos>
  <cfdi:Complemento>
    <tfd:TimbreFiscalDigital Version="1.1" UUID="F39E59EF-B4C9-4D22-B335-8A07EC8E2F40" FechaTimbrado="2023-10-22T14:24:00" NoCertificadoSAT="20001000000300022323" SelloCFD="SIMULADO" SelloSAT="SIMULADO"/>
  </cfdi:Complemento>
</cfdi:Comprobante>
