<?xml version='1.0' encoding='UTF-8'?>
<cfdi:Comprobante xmlns:cfdi="http://www.sat.gob.mx/cfd/4" xmlns:tfd="http://www.sat.gob.mx/TimbreFiscalDigital" xmlns:xsi="http://www.w3.org/2001/XMLSchema-instance" Version="4.0" Serie="A" Folio="A-441679" Fecha="2022-04-16T11:05:00" SubTotal="11347.39" Total="13162.97" TipoDeComprobante="I" MetodoPago="PUE" FormaPago="04" Moneda="MXN">
  <cfdi:Emisor Rfc="ANO850312AB1" Nombre="ACEROS DEL NORTE SA DE CV" RegimenFiscal="601"/>
  <cfdi:Receptor Rfc="LIN850101TU2" Nombre="LOGISTICA INTEGRAL NORESTE SA DE CV" UsoCFDI="G03" RegimenFiscalReceptor="601" DomicilioFiscalReceptor="64000"/>
  <cfdi:Conceptos>
    <cfdi:Concepto ClaveProdServ="31161500" Cantidad="18" ClaveUnidad="H87" Descripcion="Tornillería industrial especializada" ValorUnitario="1260.82" Importe="11347.39"/>
  </cfdi:Conceptos>
  <cfdi:Impuestos TotalImpuestosTrasladados="1815.58">
    <cfdi:Traslados>
      <cfdi:Traslado Base="11347.39" Impuesto="002" TipoFactor="Tasa" TasaOCuota="0.160000" Importe="1815.58"/>
    </cfdi:Traslados>
  </cfdi:Impuestos>
  <cfdi:Complemento>
    <tfd:TimbreFiscalDigital Version="1.1" UUID="EDAA46D6-92A9-4351-A70C-FEF2109B28F6" FechaTimbrado="2022-04-16T11:05:00" NoCertificadoSAT="20001000000300022323" SelloCFD="SIMULADO" SelloSAT="SIMULADO"/>
  </cfdi:Complemento>
</cfdi:Comprobante>
