<?xml version='1.0' encoding='UTF-8'?>
<cfdi:Comprobante xmlns:cfdi="http://www.sat.gob.mx/cfd/4" xmlns:tfd="http://www.sat.gob.mx/TimbreFiscalDigital" xmlns:xsi="http://www.w3.org/2001/XMLSchema-instance" Version="4.0" Serie="A" Folio="A-821930" Fecha="2025-03-19T18:19:00" SubTotal="26002.89" Total="30163.35" TipoDeComprobante="I" MetodoPago="PUE" FormaPago="01" Moneda="MXN">
  <cfdi:Emisor Rfc="ANO850312AB1" Nombre="ACEROS DEL NORTE SA DE CV" RegimenFiscal="601"/>
  <cfdi:Receptor Rfc="LIN850101TU2" Nombre="LOGISTICA INTEGRAL NORESTE SA DE CV" UsoCFDI="I03" RegimenFiscalReceptor="601" DomicilioFiscalReceptor="64000"/>
  <cfdi:Conceptos>
    <cfdi:Concepto ClaveProdServ="76111500" Cantidad="27" ClaveUnidad="H87" Descripcion="Servicio de mantenimiento industrial" ValorUnitario="2600.29" Importe="26002.89"/>
  </cfdi:Conceptos>
  <cfdi:Impuestos TotalImpuestosTrasladados="4160.46">
    <cfdi:Traslados>
      <cfdi:Traslado Base="26002.89" Impuesto="002" TipoFactor="Tasa" TasaOCuota="0.160000" Importe="4160.46"/>
    </cfdi:Traslados>
  </cfdi:Impuestos>
  <cfdi:Complemento>
    <tfd:TimbreFiscalDigital Version="1.1" UUID="31067454-3FD6-4776-AD1F-56DE869B813E" FechaTimbrado="2025-03-19T18:19:00" NoCertificadoSAT="20001000000300022323" SelloCFD="SIMULADO" SelloSAT="SIMULADO"/>
  </cfdi:Complemento>
</cfdi:Comprobante>
