<?xml version='1.0' encoding='UTF-8'?>
<cfdi:Comprobante xmlns:cfdi="http://www.sat.gob.mx/cfd/4" xmlns:tfd="http://www.sat.gob.mx/TimbreFiscalDigital" xmlns:xsi="http://www.w3.org/2001/XMLSchema-instance" Version="4.0" Serie="A" Folio="A-190819" Fecha="2025-02-02T16:26:00" SubTotal="13572.02" Total="15743.54" TipoDeComprobante="I" MetodoPago="PPD" FormaPago="02" Moneda="MXN">
  <cfdi:Emisor Rfc="ANO850312AB1" Nombre="ACEROS DEL NORTE SA DE CV" RegimenFiscal="601"/>
  <cfdi:Receptor Rfc="MAT010925DE5" Nombre="MATERIALES Y CONSTRUCCION SA DE CV" UsoCFDI="G01" RegimenFiscalReceptor="601" DomicilioFiscalReceptor="64000"/>
  <cfdi:Conceptos>
    <cfdi:Concepto ClaveProdServ="72103200" Cantidad="26" ClaveUnidad="H87" Descripcion="Servicio de soldadura MIG/TIG" ValorUnitario="3393.01" Importe="13572.02"/>
  </cfdi:Conceptos>
  <cfdi:Impuestos TotalImpuestosTrasladados="2171.52">
    <cfdi:Traslados>
      <cfdi:Traslado Base="13572.02" Impuesto="002" TipoFactor="Tasa" TasaOCuota="0.160000" Importe="2171.52"/>
    </cfdi:Traslados>
  </cfdi:Impuestos>
  <cfdi:Complemento>
    <tfd:TimbreFiscalDigital Version="1.1" UUID="4847B134-0435-438E-B896-873CFCBFCE05" FechaTimbrado="2025-02-02T16:26:00" NoCertificadoSAT="20001000000300022323" SelloCFD="SIMULADO" SelloSAT="SIMULADO"/>
  </cfdi:Complemento>
</cfdi:Comprobante>
