<?xml version='1.0' encoding='UTF-8'?>
<cfdi:Comprobante xmlns:cfdi="http://www.sat.gob.mx/cfd/4" xmlns:tfd="http://www.sat.gob.mx/TimbreFiscalDigital" xmlns:xsi="http://www.w3.org/2001/XMLSchema-instance" Version="4.0" Serie="A" Folio="A-347760" Fecha="2024-09-25T17:43:00" SubTotal="8565.74" Total="9936.26" TipoDeComprobante="I" MetodoPago="PUE" FormaPago="04" Moneda="MXN">
  <cfdi:Emisor Rfc="ANO850312AB1" Nombre="ACEROS DEL NORTE SA DE CV" RegimenFiscal="601"/>
  <cfdi:Receptor Rfc="FIN920315KL8" Nombre="FERRETERIA INDUSTRIAL DEL NORTE SA DE CV" UsoCFDI="I03" RegimenFiscalReceptor="601" DomicilioFiscalReceptor="64000"/>
  <cfdi:Conceptos>
    <cfdi:Concepto ClaveProdServ="31161500" Cantidad="25" ClaveUnidad="H87" Descripcion="Tornillería industrial especializada" ValorUnitario="1713.15" Importe="8565.74"/>
  </cfdi:Conceptos>
  <cfdi:Impuestos TotalImpuestosTrasladados="1370.52">
    <cfdi:Traslados>
      <cfdi:Traslado Base="8565.74" Impuesto="002" TipoFactor="Tasa" TasaOCuota="0.160000" Importe="1370.52"/>
    </cfdi:Traslados>
  </cfdi:Impuestos>
  <cfdi:Complemento>
    <tfd:TimbreFiscalDigital Version="1.1" UUID="2E90D542-7B68-4B91-85AF-BEB9C8AA9F41" FechaTimbrado="2024-09-25T17:43:00" NoCertificadoSAT="20001000000300022323" SelloCFD="SIMULADO" SelloSAT="SIMULADO"/>
  </cfdi:Complemento>
</cfdi:Comprobante>
