<?xml version='1.0' encoding='UTF-8'?>
<cfdi:Comprobante xmlns:cfdi="http://www.sat.gob.mx/cfd/4" xmlns:tfd="http://www.sat.gob.mx/TimbreFiscalDigital" xmlns:xsi="http://www.w3.org/2001/XMLSchema-instance" Version="4.0" Serie="A" Folio="A-599573" Fecha="2022-09-25T08:20:00" SubTotal="8695.13" Total="10086.35" TipoDeComprobante="I" MetodoPago="PPD" FormaPago="28" Moneda="MXN">
  <cfdi:Emisor Rfc="ANO850312AB1" Nombre="ACEROS DEL NORTE SA DE CV" RegimenFiscal="601"/>
  <cfdi:Receptor Rfc="TEC040817FG3" Nombre="TECNOLOGIA INDUSTRIAL SA DE CV" UsoCFDI="G03" RegimenFiscalReceptor="601" DomicilioFiscalReceptor="64000"/>
  <cfdi:Conceptos>
    <cfdi:Concepto ClaveProdServ="72103200" Cantidad="62" ClaveUnidad="H87" Descripcion="Servicio de soldadura MIG/TIG" ValorUnitario="869.51" Importe="8695.13"/>
  </cfdi:Conceptos>
  <cfdi:Impuestos TotalImpuestosTrasladados="1391.22">
    <cfdi:Traslados>
      <cfdi:Traslado Base="8695.13" Impuesto="002" TipoFactor="Tasa" TasaOCuota="0.160000" Importe="1391.22"/>
    </cfdi:Traslados>
  </cfdi:Impuestos>
  <cfdi:Complemento>
    <tfd:TimbreFiscalDigital Version="1.1" UUID="B198FA47-FFF9-4D03-B95E-CFAC3A491E34" FechaTimbrado="2022-09-25T08:20:00" NoCertificadoSAT="20001000000300022323" SelloCFD="SIMULADO" SelloSAT="SIMULADO"/>
  </cfdi:Complemento>
</cfdi:Comprobante>
