<?xml version='1.0' encoding='UTF-8'?>
<cfdi:Comprobante xmlns:cfdi="http://www.sat.gob.mx/cfd/4" xmlns:tfd="http://www.sat.gob.mx/TimbreFiscalDigital" xmlns:xsi="http://www.w3.org/2001/XMLSchema-instance" Version="4.0" Serie="A" Folio="A-811640" Fecha="2023-12-15T16:51:00" SubTotal="29583.9" Total="34317.32" TipoDeComprobante="I" MetodoPago="PPD" FormaPago="04" Moneda="MXN">
  <cfdi:Emisor Rfc="ANO850312AB1" Nombre="ACEROS DEL NORTE SA DE CV" RegimenFiscal="601"/>
  <cfdi:Receptor Rfc="FIN920315KL8" Nombre="FERRETERIA INDUSTRIAL DEL NORTE SA DE CV" UsoCFDI="G03" RegimenFiscalReceptor="601" DomicilioFiscalReceptor="64000"/>
  <cfdi:Conceptos>
    <cfdi:Concepto ClaveProdServ="31201500" Cantidad="37" ClaveUnidad="H87" Descripcion="Pintura epóxica industrial" ValorUnitario="3697.99" Importe="29583.9"/>
  </cfdi:Conceptos>
  <cfdi:Impuestos TotalImpuestosTrasladados="4733.42">
    <cfdi:Traslados>
      <cfdi:Traslado Base="29583.9" Impuesto="002" TipoFactor="Tasa" TasaOCuota="0.160000" Importe="4733.42"/>
    </cfdi:Traslados>
  </cfdi:Impuestos>
  <cfdi:Complemento>
    <tfd:TimbreFiscalDigital Version="1.1" UUID="A079459E-78B2-4F29-AB35-5542563DA7AB" FechaTimbrado="2023-12-15T16:51:00" NoCertificadoSAT="20001000000300022323" SelloCFD="SIMULADO" SelloSAT="SIMULADO"/>
  </cfdi:Complemento>
</cfdi:Comprobante>
